[
  {
    "api": "",
    "link": "https://windnew.newkso.ru/wind/premium84/mono.m3u8?|Referer=https://lefttoplay.xyz/&Origin=https://lefttoplay.xyz/&User-Agent=Mozilla/5.0 (Linux; Android 13; 22101316I) AppleWebKit/537.36 (KHTML, like Gecko) Chrome/122.0.6261.105 Mobile Safari/537.36",
    "title": "MoviStar+ Laliga",
    "type": "0"
  },
  {
    "api": "",
    "link": "https://zekonew.newkso.ru/zeko/premium435/mono.m3u8?|Referer=https://lefttoplay.xyz/&Origin=https://lefttoplay.xyz/&User-Agent=Mozilla/5.0 (Linux; Android 13; 22101316I) AppleWebKit/537.36 (KHTML, like Gecko) Chrome/122.0.6261.105 Mobile Safari/537.36",
    "title": "M+ Liga de Campeones",
    "type": "0"
  },
  {
    "api": "",
    "link": "https://zekonew.newkso.ru/zeko/premium436/mono.m3u8?|Referer=https://lefttoplay.xyz/&Origin=https://lefttoplay.xyz/&User-Agent=Mozilla/5.0 (Linux; Android 13; 22101316I) AppleWebKit/537.36 (KHTML, like Gecko) Chrome/122.0.6261.105 Mobile Safari/537.36",
    "title": "M+ Deportes Spain",
    "type": "0"
  },
  {
    "api": "",
    "link": "https://zekonew.newkso.ru/zeko/premium438/mono.m3u8?|Referer=https://lefttoplay.xyz/&Origin=https://lefttoplay.xyz/&User-Agent=Mozilla/5.0 (Linux; Android 13; 22101316I) AppleWebKit/537.36 (KHTML, like Gecko) Chrome/122.0.6261.105 Mobile Safari/537.36",
    "title": "M+ Deportes 2 Spain ",
    "type": "0"
  },
  {
    "api": "",
    "link": "https://dokko1new.newkso.ru/dokko1/premium526/mono.m3u8?|Referer=https://lefttoplay.xyz/&Origin=https://lefttoplay.xyz/&User-Agent=Mozilla/5.0 (Linux; Android 13; 22101316I) AppleWebKit/537.36 (KHTML, like Gecko) Chrome/122.0.6261.105 Mobile Safari/537.36",
    "title": "M+ Deportes 3 Spain",
    "type": "0"
  },
  {
    "api": "",
    "link": "https://dokko1new.newkso.ru/dokko1/premium527/mono.m3u8?|Referer=https://lefttoplay.xyz/&Origin=https://lefttoplay.xyz/&User-Agent=Mozilla/5.0 (Linux; Android 13; 22101316I) AppleWebKit/537.36 (KHTML, like Gecko) Chrome/122.0.6261.105 Mobile Safari/537.36",
    "title": "M+ Deportes 4 Spain",
    "type": "0"
  },
  {
    "api": "",
    "link": "https://dokko1new.newkso.ru/dokko1/premium528/mono.m3u8?|Referer=https://lefttoplay.xyz/&Origin=https://lefttoplay.xyz/&User-Agent=Mozilla/5.0 (Linux; Android 13; 22101316I) AppleWebKit/537.36 (KHTML, like Gecko) Chrome/122.0.6261.105 Mobile Safari/537.36",
    "title": "M+ Golf Spain",
    "type": "0"
  }
]