[
  {
    "api": "",
    "link": "https://soccerfull.net/hls/14534.m3u8",
    "logo": "",
    "title": "HIGHLIGHTS [EN]",
    "type": "0"
  },
  {
    "api": "",
    "link": "https://fullmatchshows.embedseek.com/hlsmod/p16-ad-site-sign-sg.tiktokcdn.com/FGmWF5D14hisAnUaLQVP8g/ho/9dr5kb6n/vp6n9n/tt/master.m3u8",
    "logo": "",
    "title": "HIGHLIGHTS",
    "type": "0"
  },
  {
    "api": "",
    "link": "https://fullmatchshows.embedseek.com/hlsmod/p16-ad-site-sign-sg.tiktokcdn.com/KMRtDHIr42l0pCDPq5DDmA/5c/9dr5kb6n/e3n1ut/tt/master.m3u8",
    "logo": "",
    "title": "EX. HIGHLIGHTS",
    "type": "0"
  },
  {
    "api": "",
    "link": "https://fullmatchshows.embedseek.com/hlsmod/p16-ad-site-sign-sg.tiktokcdn.com/ahpbRTRJKJmS9RuA4SiYyA/6s/9dr5kb6n/9w36db/tt/master.m3u8",
    "logo": "",
    "title": "FULL MATCH",
    "type": "0"
  },
  {
    "api": "",
    "link": "https://fullmatchshows.embedseek.com/hlsmod/p16-ad-site-sign-sg.tiktokcdn.com/UUN-hOPtKsfHSQVwrKwfQg/xy/9dr5kb6n/gqoacw/tt/master.m3u8",
    "logo": "",
    "title": "FULL MATCH [RU]",
    "type": "0"
  }
]